c27cache/__init__.py
c27cache/backend.py
c27cache/config.py
c27cache/datetime_support.py
c27cache/expiry.py
c27cache/keys.py
c27cache/logger.py
c27cache/service.py
c27cache-0.1.6.dist-info/WHEEL
c27cache-0.1.6.dist-info/METADATA
c27cache-0.1.6.dist-info/RECORD
