Metadata-Version: 2.1
Name: c27cache
Version: 0.1.6
Summary: A simple caching library.
Home-page: https://gitlab.com/core-27/c27cache.git
License: Apache-2.0
Keywords: fastapi,caching,cache,simple
Author: ragequilt
Author-email: sid.ravichandran@gmail.com
Requires-Python: >=3.8,<4.0
Classifier: License :: OSI Approved :: Apache Software License
Classifier: Programming Language :: Python :: 3
Classifier: Programming Language :: Python :: 3.10
Classifier: Programming Language :: Python :: 3.8
Classifier: Programming Language :: Python :: 3.9
Requires-Dist: pytest-asyncio (==0.15.1)
Requires-Dist: python-dateutil (>=2.8.2,<3.0.0)
Requires-Dist: pytz (>=2021.3,<2022.0)
Requires-Dist: redis (==3.5.3)
Project-URL: Documentation, https://gitlab.com/core-27/c27cache
Project-URL: Repository, https://gitlab.com/core-27/c27cache.git
